_shortfin/__init__.py
_shortfin/asyncio_bridge.py
_shortfin_default/__init__.py
_shortfin_default/lib.cpython-313-x86_64-linux-gnu.so
_shortfin_default/__pycache__/__init__.cpython-313.pyc
_shortfin_default/lib/__init__.pyi
_shortfin_default/lib/array.pyi
_shortfin_default/lib/local.pyi
_shortfin_tracy/__init__.py
_shortfin_tracy/lib.cpython-313-x86_64-linux-gnu.so
_shortfin_tracy/__pycache__/__init__.cpython-313.pyc
_shortfin_tracy/lib/__init__.pyi
_shortfin_tracy/lib/array.pyi
_shortfin_tracy/lib/local.pyi
shortfin/__init__.py
shortfin/amdgpu.py
shortfin/host.py
shortfin/array/__init__.py
shortfin/array/_nputils.py
shortfin/interop/fastapi/__init__.py
shortfin/interop/support/device_setup.py
shortfin/interop/support/logging_setup.py
shortfin/support/deps.py
shortfin/support/logging_setup.py
shortfin/support/responder.py
shortfin/support/status_tracker.py
shortfin.libs/libshortfin-16539b35.so.3.9.0
shortfin.libs/libshortfin-e1f79077.so.3.9.0
shortfin_apps/utils.py
shortfin_apps/flux/__init__.py
shortfin_apps/flux/_deps.py
shortfin_apps/flux/server.py
shortfin_apps/flux/simple_client.py
shortfin_apps/flux/components/builders.py
shortfin_apps/flux/components/config_artifacts.py
shortfin_apps/flux/components/config_struct.py
shortfin_apps/flux/components/generate.py
shortfin_apps/flux/components/io_struct.py
shortfin_apps/flux/components/manager.py
shortfin_apps/flux/components/messages.py
shortfin_apps/flux/components/metrics.py
shortfin_apps/flux/components/service.py
shortfin_apps/flux/components/tokenizer.py
shortfin_apps/llm/__init__.py
shortfin_apps/llm/_deps.py
shortfin_apps/llm/application.py
shortfin_apps/llm/benchmark_client.py
shortfin_apps/llm/cli.py
shortfin_apps/llm/client.py
shortfin_apps/llm/server.py
shortfin_apps/llm/components/__init__.py
shortfin_apps/llm/components/buffers.py
shortfin_apps/llm/components/config_struct.py
shortfin_apps/llm/components/decode_config.py
shortfin_apps/llm/components/device_array_cache.py
shortfin-3.9.0.dist-info/METADATA
shortfin-3.9.0.dist-info/WHEEL
shortfin-3.9.0.dist-info/top_level.txt
shortfin-3.9.0.dist-info/RECORD
