Metadata-Version: 2.4
Name: shortfin
Version: 3.9.0
Summary: amdshark inference library and serving engine
Author: amdshark Authors
License-Expression: Apache-2.0
Project-URL: Repository, https://github.com/nod-ai/amd-shark-ai
Project-URL: Documentation, https://shortfin.readthedocs.io/en/latest/
Classifier: Development Status :: 3 - Alpha
Classifier: Programming Language :: Python :: 3
Classifier: Programming Language :: Python :: 3.10
Classifier: Programming Language :: Python :: 3.11
Classifier: Programming Language :: Python :: 3.12
Classifier: Programming Language :: Python :: 3.13
Requires-Python: >=3.10
Provides-Extra: apps
Requires-Dist: transformers; extra == "apps"
Requires-Dist: dataclasses-json; extra == "apps"
Requires-Dist: pillow; extra == "apps"
Requires-Dist: fastapi; extra == "apps"
Requires-Dist: uvicorn; extra == "apps"
Requires-Dist: aiohttp>=3.11.3; extra == "apps"
